Workbook

Sheet Item Master Ref
A1: SKU | B1: Desc | C1: Check
A2: 2511-0001 | B2: MR672F, Penetrant - Flourescent Level 2; Solvent & Water Removable (400ml) | C2: =VLOOKUP(A2,'Product Categories for FG'!A$2:A$269,1,0) -> 2511-0001
A3: 2511-0002 | B3: MR231, Dry Magnetic Powder - Grey (1Kg) | C3: =VLOOKUP(A3,'Product Categories for FG'!A$2:A$269,1,0) -> 2511-0002
A4: 2511-0003 | B4: MR62, Penetrant - Red; Solvent Removable (400 ml) | C4: =VLOOKUP(A4,'Product Categories for FG'!A$2:A$269,1,0) -> 2511-0003
A5: 2511-0004 | B5: MR68NF, Biodegradable Penetrant – Red & Fluorescent; Solvent & Water Removable (400ml) | C5: =VLOOKUP(A5,'Product Categories for FG'!A$2:A$269,1,0) -> 2511-0004
A6: 2511-0005 | B6: MR311-R AMS, Penetrant - Red; Solvent & Water Removable (400 ml) | C6: =VLOOKUP(A6,'Product Categories for FG'!A$2:A$269,1,0) -> 2511-0005
A7: 2511-0006 | B7: MR70, Developer - White, Non Aqueous (400 ml) | C7: =VLOOKUP(A7,'Product Categories for FG'!A$2:A$269,1,0) -> 2511-0006
A8: 2511-0007 | B8: MR70I, Developer - White, Non Aqueous (400 ml) | C8: =VLOOKUP(A8,'Product Categories for FG'!A$2:A$269,1,0) -> 2511-0007
A9: 2511-0008 | B9: MR79, Special Remover (400 ml) | C9: =VLOOKUP(A9,'Product Categories for FG'!A$2:A$269,1,0) -> 2511-0008
A10: 2511-0009 | B10: MR85, Remover (400 ml) | C10: =VLOOKUP(A10,'Product Categories for FG'!A$2:A$269,1,0) -> 2511-0009
A11: 2511-0010 | B11: MR311-R (Non AMS), Penetrant - Red; Solvent & Water Removable (400 ml) | C11: =VLOOKUP(A11,'Product Categories for FG'!A$2:A$269,1,0) -> 2511-0010
A12: 2511-0011 | B12: MR70I (HD), Developer - White, Non Aqueous (400 ml) | C12: =VLOOKUP(A12,'Product Categories for FG'!A$2:A$269,1,0) -> 2511-0011
A13: 2511-0012 | B13: MR76S, Magnetic Powder Suspension - Black (400 ml) | C13: =VLOOKUP(A13,'Product Categories for FG'!A$2:A$269,1,0) -> 2511-0012
... A251: 2511-0280 | B251: Magnetic Field Indicator Acc to ASTM E -709(Pie Guage) | C251: =VLOOKUP(A251,'Product Categories for FG'!A$2:A$269,1,0) -> 2511-0280
A252: 2511-0281 | C252: =VLOOKUP(A252,'Product Categories for FG'!A$2:A$269,1,0) -> 2511-0281
A253: 2511-0283 | B253: Penetrant Testing Flawed Specimen | C253: =VLOOKUP(A253,'Product Categories for FG'!A$2:A$269,1,0) -> 2511-0283

Sheet Indian State Categorisation
A1: Code | B1: Description | C1: State Code for eTDS/TCS | D1: State Code (GST Reg. No.) | E1: Zone
A2: AD | B2: Andhra Pradesh | C2: 2 | D2: 37 | E2: South
A3: AN | B3: Andaman and Nicobar Islands | C3: 1 | D3: 35 | E3: South
A4: AR | B4: Arunachal Pradesh | C4: 3 | D4: 12 | E4: North East
A5: AS | B5: Assam | C5: 4 | D5: 18 | E5: North East
A6: BR | B6: Bihar | C6: 5 | D6: 10 | E6: East
A7: CG | B7: Chattisgarh | C7: 33 | D7: 22 | E7: Central
A8: CH | B8: Chandigarh | C8: 6 | D8: 4 | E8: North
A9: DD | B9: Daman and Diu | C9: 8 | D9: 25 | E9: West
A10: DL | B10: Delhi | C10: 9 | D10: 7 | E10: North
A11: DN | B11: Dadra and Nagar Haveli | C11: 7 | D11: 26 | E11: West
A12: GA | B12: Goa | C12: 10 | D12: 30 | E12: West
A13: GJ | B13: Gujarat | C13: 11 | D13: 24 | E13: West
... A38: WB | B38: West Bengal | C38: 32 | D38: 19 | E38: East

Sheet FG Product Categorisation
A1: SKU | B1: Name | C1: Master Category | D1: Category | E1: Sub Category | F1: Product Base Name | G1: Check ERP
A2: 2511-0001 | B2: MR672F, Penetrant - Flourescent Level 2; Solvent & Water Removable (400ml) | C2: Non Destructive Testing Solutions | D2: Dye Penetrant Testing | E2: Penetrant | F2: MR672F
A3: 2511-0002 | B3: MR231, Dry Magnetic Powder - Grey (1Kg) | C3: Non Destructive Testing Solutions | D3: Magnetic Particle Testing | E3: Dry Powders | F3: MR231
A4: 2511-0003 | B4: MR62, Penetrant - Red; Solvent Removable (400 ml) | C4: Non Destructive Testing Solutions | D4: Dye Penetrant Testing | E4: Penetrant | F4: MR62
A5: 2511-0004 | B5: MR68NF, Biodegradable Penetrant – Red & Fluorescent; Solvent & Water Removable (400ml) | C5: Non Destructive Testing Solutions | D5: Dye Penetrant Testing | E5: Penetrant | F5: MR68NF
A6: 2511-0005 | B6: MR311-R AMS, Penetrant - Red; Solvent & Water Removable (400 ml) | C6: Non Destructive Testing Solutions | D6: Dye Penetrant Testing | E6: Penetrant | F6: MR311-R
A7: 2511-0006 | B7: MR70, Developer - White, Non Aqueous (400 ml) | C7: Non Destructive Testing Solutions | D7: Dye Penetrant Testing | E7: Developer | F7: MR70
A8: 2511-0007 | B8: MR70I, Developer - White, Non Aqueous (400 ml) | C8: Non Destructive Testing Solutions | D8: Dye Penetrant Testing | E8: Developer | F8: MR70I
A9: 2511-0008 | B9: MR79, Special Remover (400 ml) | C9: Non Destructive Testing Solutions | D9: Dye Penetrant Testing | E9: Cleaner | F9: MR79
A10: 2511-0009 | B10: MR85, Remover (400 ml) | C10: Non Destructive Testing Solutions | D10: Dye Penetrant Testing | E10: Cleaner | F10: MR85
A11: 2511-0010 | B11: MR311-R (Non AMS), Penetrant - Red; Solvent & Water Removable (400 ml) | C11: Non Destructive Testing Solutions | D11: Dye Penetrant Testing | E11: Penetrant | F11: MR311-R
A12: 2511-0011 | B12: MR70I (HD), Developer - White, Non Aqueous (400 ml) | C12: Non Destructive Testing Solutions | D12: Dye Penetrant Testing | E12: Developer | F12: MR70I
A13: 2511-0012 | B13: MR76S, Magnetic Powder Suspension - Black (400 ml) | C13: Non Destructive Testing Solutions | D13: Magnetic Particle Testing | E13: Detection Media (Visible) | F13: MR76S
... A243: 2511-0272 | B243: MR68NF, Biodegradable Penetrant – Red & Fluorescent; Solvent & Water Removable (Piccolo-Pen) | C243: Non Destructive Testing Solutions | D243: NA | E243: NA | F243: NA
A244: 2511-0273 | B244: Consolidated Old Balance FG | D244: NA | E244: NA | F244: NA
A245: 2511-0274 | B245: AC/DC Yoke | C245: Non Destructive Testing Solutions | D245: NA | E245: NA | F245: NA
A246: 2511-0275 | B246: 20-0-20 Gauss Meter | C246: Non Destructive Testing Solutions | D246: NA | E246: NA | F246: NA
A247: 2511-0276 | B247: Centrifugal Tube with Stand | C247: Non Destructive Testing Solutions | D247: NA | E247: NA | F247: NA
A248: 2511-0277 | B248: Calcium Carbonate | D248: NA | E248: NA | F248: NA
A249: 2511-0278 | B249: UVA LED Flashlight | C249: Non Destructive Testing Solutions | D249: NA | E249: NA | F249: NA
A250: 2511-0279 | B250: Resinwork DENTSIN Pro Aqua 2 (Birch Beige) - 1 kg | C250: 3D Printing | D250: Resin | E250: NA | F250: NA
A251: 2511-0280 | B251: Magnetic Field Indicator Acc to ASTM E -709(Pie Guage) | C251: Non Destructive Testing Solutions | D251: NA | E251: NA | F251: NA
A252: 2511-0281 | B252: NA | C252: NA | D252: NA | E252: NA | F252: NA
A253: 2511-0283 | B253: Penetrant Testing Flawed Specimen | C253: Non Destructive Testing Solutions | D253: NA | E253: NA | F253: NA

Sheet Quickbooks DataClean
A1: PRODUCT | B1: SKU 1
A2: 3D Resin Development for ATTBLIME | B2: 2511-
A3: Aquakleen - General Purpose Industrial Cleaner and Degreaser Water-Based Concentrate (5L) Can (HSN CODE 34029092) | B3: 2511-0116
A4: Aquakleen - General Purpose Industrial Cleaner and Degreaser Water-Based Concentrate (5L) Can (HSN CODE 34029092) Free Sample | B4: 2511-0116
A5: Aquakleen - General Purpose Industrial Cleaner and Degreaser Water-Based Concentrate (5L) Cans (HSN CODE 34029092) | B5: 2511-0116
A6: Articulation piece for articulated poles for hand yoke MR® 56, MR® 56V42, MR® 56V110 1 set = 2 pieces | B6: 2511-
A7: ATTBLIME AB 24 (400ml) (HSN CODE 3212900050) | B7: 2511-0170
A8: Attblime AB ECO 1 Ltr (HSN CODE 32129000) | B8: 2511-
A9: ATTBLIME AB ZERO (400ml) (HSN CODE 3212900050) | B9: 2511-
A10: ATTBLIME AB ZERO (400ml) (HSN OCDE 32129000) | B10: 2511-
A11: ATTBLIME- AB2 (400ml) (HSN CODE 32064990) | B11: 2511-0171
A12: ATTBLIME- AB2 (400ml) (HSN CODE 32129000) | B12: 2511-0171
... A297: Warehouse Handling (D.G2.1) | B297: 2511-

Sheet Product Categories for FG
A1: SKU | B1: Name | C1: Master Category | D1: Category | E1: Sub Category | F1: Product Base Name | G1: Product Manufacturig Reference | H1: Batch Size | I1: Big Batch Size | J1: BomNo | K1: Package Type | L1: Box Type | M1: Case Qty | N1: Haze Class | O1: Old SKU Number | P1: Royalty
A2: 2511-0001 | B2: MR672F, Penetrant - Flourescent Level 2; Solvent & Water Removable (400ml) | C2: Non Destructive Testing | D2: Dye Penetrant Testing | E2: Penetrant | F2: MR672F | G2: MR672F | H2: NA | I2: NA | J2: 171005 | K2: BULK 5L | L2: JAR J1 | M2: 5 | N2: NON DG | O2: 0 | P2: =VLOOKUP(F2,Royalty!$A$3:$B$49,2,0) -> 2
A3: 2511-0002 | B3: MR231, Dry Magnetic Powder - Grey (1Kg) | C3: Non Destructive Testing | D3: Magnetic Particle Testing | E3: Dry Powders | F3: MR231 | G3: MR231 | H3: NA | I3: NA | J3: 172023 | K3: BULK 1KG | L3: BOX A1 | M3: 8 | N3: NON DG | O3: 172023 | P3: =VLOOKUP(F3,Royalty!$A$3:$B$49,2,0) -> 2
A4: 2511-0003 | B4: MR62, Penetrant - Red; Solvent Removable (400 ml) | C4: Non Destructive Testing | D4: Dye Penetrant Testing | E4: Penetrant | F4: MR62 | G4: MR62 | H4: NA | I4: NA | J4: 171014 | K4: BULK 1L | L4: BOX B1 | M4: 6 | N4: NON DG | O4: 0 | P4: =VLOOKUP(F4,Royalty!$A$3:$B$49,2,0) -> 2
A5: 2511-0004 | B5: MR68NF, Biodegradable Penetrant – Red & Fluorescent; Solvent & Water Removable (400ml) | C5: Non Destructive Testing | D5: Dye Penetrant Testing | E5: Penetrant | F5: MR68NF | G5: MR68NF | H5: NA | I5: NA | J5: 171022 | K5: BULK 5L | L5: BOX B2 | M5: 5 | N5: NON DG | O5: 171003 | P5: =VLOOKUP(F5,Royalty!$A$3:$B$49,2,0) -> 3
A6: 2511-0005 | B6: MR311-R AMS, Penetrant - Red; Solvent & Water Removable (400 ml) | C6: Non Destructive Testing | D6: Dye Penetrant Testing | E6: Penetrant | F6: MR311-R | G6: MR311-R | H6: NA | I6: NA | J6: 171025 | K6: BULK 205L | L6: BAR L1 | M6: 205 | N6: NON DG | O6: 171004 | P6: =VLOOKUP(F6,Royalty!$A$3:$B$49,2,0) -> 3
A7: 2511-0006 | B7: MR70, Developer - White, Non Aqueous (400 ml) | C7: Non Destructive Testing | D7: Dye Penetrant Testing | E7: Developer | F7: MR70 | G7: MR70 | H7: NA | I7: NA | J7: 171028 | K7: BULK 5L | L7: JAR J1 | M7: 5 | N7: DG 3 | O7: 0 | P7: =VLOOKUP(F7,Royalty!$A$3:$B$49,2,0) -> 3
A8: 2511-0007 | B8: MR70I, Developer - White, Non Aqueous (400 ml) | C8: Non Destructive Testing | D8: Dye Penetrant Testing | E8: Developer | F8: MR70I | G8: MR70I | H8: NA | I8: NA | J8: 171031 | K8: PICCOLO PEN | L8: BOX CL | M8: 1 | N8: DG 3 | O8: 0 | P8: =VLOOKUP(F8,Royalty!$A$3:$B$49,2,0) -> 2
A9: 2511-0008 | B9: MR79, Special Remover (400 ml) | C9: Non Destructive Testing | D9: Dye Penetrant Testing | E9: Cleaner | F9: MR79 | G9: MR79 | H9: NA | I9: NA | J9: 171035 | K9: BULK 5L | L9: JAR J1 | M9: 5 | N9: DG 3 | O9: 0 | P9: =VLOOKUP(F9,Royalty!$A$3:$B$49,2,0) -> 3
A10: 2511-0009 | B10: MR85, Remover (400 ml) | C10: Non Destructive Testing | D10: Dye Penetrant Testing | E10: Cleaner | F10: MR85 | G10: MR85 | H10: NA | I10: NA | J10: 171038 | K10: PICCOLO PEN | L10: BOX CL | M10: 1 | N10: DG 3 | O10: 0 | P10: =VLOOKUP(F10,Royalty!$A$3:$B$49,2,0) -> 3
A11: 2511-0010 | B11: MR311-R (Non AMS), Penetrant - Red; Solvent & Water Removable (400 ml) | C11: Non Destructive Testing | D11: Dye Penetrant Testing | E11: Penetrant | F11: MR311-R | G11: MR311-R | H11: NA | I11: NA | J11: 171041 | K11: BULK 5L | L11: BOX A1 | M11: 5 | N11: NON DG | O11: 171024 | P11: =VLOOKUP(F11,Royalty!$A$3:$B$49,2,0) -> 3
A12: 2511-0011 | B12: MR70I (HD), Developer - White, Non Aqueous (400 ml) | C12: Non Destructive Testing | D12: Dye Penetrant Testing | E12: Developer | F12: MR70I | G12: MR70I | H12: NA | I12: NA | J12: 171044 | K12: BULK 1KG | L12: JAR J1 | M12: 1 | N12: NON DG | O12: 171034 | P12: =VLOOKUP(F12,Royalty!$A$3:$B$49,2,0) -> 2
A13: 2511-0012 | B13: MR76S, Magnetic Powder Suspension - Black (400 ml) | C13: Non Destructive Testing | D13: Magnetic Particle Testing | E13: Detection Media (Visible) | F13: MR76S | G13: MR76S | H13: NA | I13: NA | J13: 172001 | K13: BULK 1KG | L13: BOX B1 | M13: 1 | N13: NON DG | O13: 172002 | P13: =VLOOKUP(F13,Royalty!$A$3:$B$49,2,0) -> 2
... A15: 2511-0014 | B15: MR761F, ECOLINE Magnetic Powder Suspension - Fluorescent (400 ml) | C15: Non Destructive Testing | D15: Magnetic Particle Testing | E15: Detection Media (Fluorescent) | F15: MR761F | G15: MR761F | H15: NA | I15: NA | J15: 172008 | K15: BULK 1KG | L15: BOX B1 | M15: 6 | N15: NON DG | O15: 172010 | P15: =VLOOKUP(F15,Royalty!$A$3:$B$49,2,0) -> 2
A16: 2511-0015 | B16: MR72 OR, White Contrast Paint (400 ml) | C16: Non Destructive Testing | D16: Magnetic Particle Testing | E16: Contrast Paint | F16: MR72 | G16: MR72 OR | H16: 12000 | I16: NA | J16: 172027 | K16: AEROSOL 400ML | L16: BOX A1 | M16: 10 | N16: UN1950 | O16: 172027 | P16: =VLOOKUP(F16,Royalty!$A$3:$B$49,2,0) -> 2
A17: 2511-0016 | B17: MR71, Paint Remover (400 ml) | C17: Non Destructive Testing | D17: Magnetic Particle Testing | E17: Cleaner | F17: MR71 | G17: MR71 | H17: NA | I17: NA | J17: 172035 | K17: BULK 20L | L17: JAR J2 | M17: 20 | N17: NON DG | O17: 0 | P17: =VLOOKUP(F17,Royalty!$A$3:$B$49,2,0) -> 3
A18: 2511-0017 | B18: MR72 EZ, White Contrast Paint (400 ml) | C18: Non Destructive Testing | D18: Magnetic Particle Testing | E18: Contrast Paint | F18: MR72 | G18: MR72 EZ | H18: NA | I18: NA | J18: 172038 | K18: AEROSOL 400ML | L18: BOX A1 | M18: 10 | N18: UN1950 | O18: 172038 | P18: =VLOOKUP(F18,Royalty!$A$3:$B$49,2,0) -> 2
A19: 2511-0018 | B19: MR72 HD, White Contrast Paint (400 ml) | C19: Non Destructive Testing | D19: Magnetic Particle Testing | E19: Contrast Paint | F19: MR72 | G19: MR72 HD | H19: 12000 | I19: NA | J19: 172039 | K19: AEROSOL 400ML | L19: BOX A1 | M19: 10 | N19: UN1950 | O19: 172039 | P19: =VLOOKUP(F19,Royalty!$A$3:$B$49,2,0) -> 2
A20: 2511-0019 | B20: MR72 AU, White Contrast Paint (400 ml) | C20: Non Destructive Testing | D20: Magnetic Particle Testing | E20: Contrast Paint | F20: MR72 | G20: MR72 AU | H20: NA | I20: NA | J20: 172040 | K20: AEROSOL 400ML | L20: BOX A1 | M20: 10 | N20: UN1950 | O20: 172040 | P20: =VLOOKUP(F20,Royalty!$A$3:$B$49,2,0) -> 2
A21: 2511-0020 | B21: MR72 IN, White Contrast Paint (400 ml) | C21: Non Destructive Testing | D21: Magnetic Particle Testing | E21: Contrast Paint | F21: MR72 | G21: MR72 IN | H21: 12000 | I21: NA | J21: 172041 | K21: AEROSOL 400ML | L21: BOX A1 | M21: 1 | N21: UN1950 | O21: 172041 | P21: =VLOOKUP(F21,Royalty!$A$3:$B$49,2,0) -> 2
A22: 2511-0021 | B22: MR233, Dry Magnetic Powder - Yellow (1Kg) | C22: Non Destructive Testing | D22: Magnetic Particle Testing | E22: Dry Powders | F22: MR233 | G22: MR233 | H22: NA | I22: NA | J22: 172025 | K22: BULK 1KG | L22: BOX A1 | M22: 8 | N22: NON DG | O22: 172025 | P22: =VLOOKUP(F22,Royalty!$A$3:$B$49,2,0) -> 2
A23: 2511-0022 | B23: MR234, Dry Magnetic Powder - Blue (1Kg) | C23: Non Destructive Testing | D23: Magnetic Particle Testing | E23: Dry Powders | F23: MR234 | G23: MR234 | H23: NA | I23: NA | J23: 172026 | K23: BULK 1KG | L23: BOX A1 | M23: 8 | N23: NON DG | O23: 172026 | P23: =VLOOKUP(F23,Royalty!$A$3:$B$49,2,0) -> 2
A24: 2511-0023 | B24: MR683F, Penetrant - Flourescent Level 3; Solvent Removable (400 ml) | C24: Non Destructive Testing | D24: Dye Penetrant Testing | E24: Penetrant | F24: MR683F | G24: MR683F | H24: NA | I24: NA | J24: 171010 | K24: AEROSOL 400ML | L24: BOX A1 | M24: 10 | N24: UN1950 | O24: 171022 | P24: =VLOOKUP(F24,Royalty!$A$3:$B$49,2,0) -> 2
A25: 2511-0024 | B25: MR110, ECOLINE Magnetic Powder - Fluorescent (1/2Kg) | C25: Non Destructive Testing | D25: Magnetic Particle Testing | E25: Detection Media (Fluorescent) | F25: MR110 | G25: MR110 | H25: NA | I25: NA | J25: 172009 | K25: BULK 1/2KG | L25: BOX A1 | M25: 3 | N25: NON DG | O25: 172011 | P25: =VLOOKUP(F25,Royalty!$A$3:$B$49,2,0) -> 3
A26: 2511-0025 | B26: MR111HB, ECOLINE Magnetic Powder - Fluorescent (1/2Kg) | C26: Non Destructive Testing | D26: Magnetic Particle Testing | E26: Detection Media (Fluorescent) | F26: MR111HB | G26: MR111HB | H26: NA | I26: NA | J26: 172011 | K26: BULK 1KG | L26: BOX B1 | M26: 6 | N26: NON DG | O26: 172012 | P26: =VLOOKUP(F26,Royalty!$A$3:$B$49,2,0) -> 2
A27: 2511-0026 | B27: MR112, ECOLINE Magnetic Powder - Fluorescent (1/2Kg) | C27: Non Destructive Testing | D27: Magnetic Particle Testing | E27: Detection Media (Fluorescent) | F27: MR112 | G27: MR112 | H27: NA | I27: NA | J27: 172013 | K27: BULK 1/2KG | L27: BOX CL | M27: 1 | N27: NON DG | O27: 172011 | P27: =VLOOKUP(F27,Royalty!$A$3:$B$49,2,0) -> 2
A28: 2511-0027 | B28: MR222, ECOLINE Magnetic Powder - Red & Fluorescent (1Kg) | C28: Non Destructive Testing | D28: Magnetic Particle Testing | E28: Detection Media (Fluorescent) | F28: MR222 | G28: MR222 | H28: NA | I28: NA | J28: 172005 | K28: BULK 1/2KG | L28: BOX A1 | M28: 1 | N28: NON DG | O28: 172011 | P28: =VLOOKUP(F28,Royalty!$A$3:$B$49,2,0) -> 2
A29: 2511-0028 | B29: MR81T-R, Dry Developer Powder (1Kg) | C29: Non Destructive Testing | D29: Dye Penetrant Testing | E29: Developer | F29: MR81T-R | G29: MR81T-R | H29: NA | I29: NA | J29: 171034 | K29: BULK 1KG | L29: JAR J1 | M29: 1 | N29: NON DG | O29: 0 | P29: =VLOOKUP(F29,Royalty!$A$3:$B$49,2,0) -> 2
A30: 2511-0029 | B30: MR210, ECOLINE Magnetic Powder - Black (1Kg) | C30: Non Destructive Testing | D30: Magnetic Particle Testing | E30: Detection Media (Visible) | F30: MR210 | G30: MR210 | H30: NA | I30: NA | J30: 172002 | K30: BULK 1KG | L30: BOX B1 | M30: 1 | N30: NON DG | O30: 172004 | P30: =VLOOKUP(F30,Royalty!$A$3:$B$49,2,0) -> 3
A31: 2511-0030 | B31: MR214, Magnetic Powder Concentrate - Black (1Kg) | C31: Non Destructive Testing | D31: Magnetic Particle Testing | E31: Detection Media (Visible) | F31: MR214 | G31: MR214 | H31: NA | I31: NA | J31: 172004 | K31: BULK 1L | L31: BOX B1 | M31: 6 | N31: NON DG | O31: 172003 | P31: =VLOOKUP(F31,Royalty!$A$3:$B$49,2,0) -> 2
A32: 2511-0031 | B32: MR114HB, Magnetic Powder Composition - Fluorescent 'high brilliance' (1Kg) | C32: Non Destructive Testing | D32: Magnetic Particle Testing | E32: Detection Media (Fluorescent) | F32: MR114HB | G32: MR114HB | H32: NA | I32: NA | J32: 172015 | K32: BULK 1KG | L32: BOX CL | M32: 1 | N32: NON DG | O32: 172012 | P32: =VLOOKUP(F32,Royalty!$A$3:$B$49,2,0) -> 2
A33: 2511-0032 | B33: MR110, ECOLINE Magnetic Powder - Fluorescent (1Kg) | C33: Non Destructive Testing | D33: Magnetic Particle Testing | E33: Detection Media (Fluorescent) | F33: MR110 | G33: MR110 | H33: NA | I33: NA | J33: 172010 | K33: BULK 1KG | L33: BOX B1 | M33: 1 | N33: NON DG | O33: 172012 | P33: =VLOOKUP(F33,Royalty!$A$3:$B$49,2,0) -> 3
... A40: 2511-0039 | B40: MR304, Water Conditioner (1Kg) | C40: Non Destructive Testing | D40: Magnetic Particle Testing | E40: Additives | F40: MR304 | G40: MR304 | H40: NA | I40: NA | J40: 172034 | K40: BULK 1KG | L40: BOX B1 | M40: 6 | N40: NON DG | O40: 172034 | P40: =VLOOKUP(F40,Royalty!$A$3:$B$49,2,0) -> 2
A41: 2511-0040 | B41: MR913-Y, Leak Detector concentrate, oil based (fluorescent - yellow) (1L) | C41: Non Destructive Testing | D41: Leak Detection Systems | E41: Leak Detection Dye | F41: NA | G41: NA | H41: NA | I41: NA | J41: 171013 | K41: BULK 1L | L41: BOX B1 | M41: 6 | N41: NON DG | O41: 171013
A42: 2511-0041 | B42: MR62, Penetrant - Red; Solvent Removable (1L) | C42: Non Destructive Testing | D42: Dye Penetrant Testing | E42: Penetrant | F42: MR62 | G42: MR62 | H42: NA | I42: NA | J42: 171015 | K42: BULK 1L | L42: BOX B1 | M42: 6 | N42: NON DG | O42: 171023 | P42: =VLOOKUP(F42,Royalty!$A$3:$B$49,2,0) -> 2
A43: 2511-0042 | B43: MR67, ECOLINE Penetrant - Red; Solvent & Water Removable (1L) | C43: Non Destructive Testing | D43: Dye Penetrant Testing | E43: Penetrant | F43: MR67 | G43: MR67 | H43: NA | I43: NA | J43: 171020 | K43: BULK 5L | L43: BOX B2 | M43: 5 | N43: NON DG | O43: 171011 | P43: =VLOOKUP(F43,Royalty!$A$3:$B$49,2,0) -> 3
A44: 2511-0043 | B44: MR68NF, Biodegradable Penetrant – Red & Fluorescent; Solvent & Water Removable (1L) | C44: Non Destructive Testing | D44: Dye Penetrant Testing | E44: Penetrant | F44: MR68NF | G44: MR68NF | H44: NA | I44: NA | J44: 171023 | K44: AEROSOL 400ML | L44: BOX A1 | M44: 10 | N44: UN1950 | O44: 171010 | P44: =VLOOKUP(F44,Royalty!$A$3:$B$49,2,0) -> 3
A45: 2511-0044 | B45: MR311-R AMS, Penetrant - Red; Solvent & Water Removable (1L) | C45: Non Destructive Testing | D45: Dye Penetrant Testing | E45: Penetrant | F45: MR311-R | G45: MR311-R | H45: NA | I45: NA | J45: 171026 | K45: BULK 205L | L45: BAR L1 | M45: 205 | N45: NON DG | O45: 171012 | P45: =VLOOKUP(F45,Royalty!$A$3:$B$49,2,0) -> 3
A46: 2511-0045 | B46: MR70, Developer - White, Non Aqueous (1L) | C46: Non Destructive Testing | D46: Dye Penetrant Testing | E46: Developer | F46: MR70 | G46: MR70 | H46: NA | I46: NA | J46: 171029 | K46: BULK 5L | L46: BOX B2 | M46: 5 | N46: DG 3 | O46: 171033 | P46: =VLOOKUP(F46,Royalty!$A$3:$B$49,2,0) -> 3
A47: 2511-0046 | B47: MR70I, Developer - White, Non Aqueous (1L) | C47: Non Destructive Testing | D47: Dye Penetrant Testing | E47: Developer | F47: MR70I | G47: MR70I | H47: NA | I47: NA | J47: 171032 | K47: AEROSOL 400ML | L47: BOX A1 | M47: 10 | N47: UN1950 | O47: 171031 | P47: =VLOOKUP(F47,Royalty!$A$3:$B$49,2,0) -> 2
A48: 2511-0047 | B48: MR79, Special Remover (1L) | C48: Non Destructive Testing | D48: Dye Penetrant Testing | E48: Cleaner | F48: MR79 | G48: MR79 | H48: NA | I48: NA | J48: 171036 | K48: BULK 5L | L48: BOX B2 | M48: 5 | N48: DG 3 | O48: 171040 | P48: =VLOOKUP(F48,Royalty!$A$3:$B$49,2,0) -> 3
A49: 2511-0048 | B49: MR85, Remover (1L) | C49: Non Destructive Testing | D49: Dye Penetrant Testing | E49: Cleaner | F49: MR85 | G49: MR85 | H49: NA | I49: NA | J49: 171039 | K49: AEROSOL 400ML | L49: BOX A1 | M49: 10 | N49: UN1950 | O49: 171038 | P49: =VLOOKUP(F49,Royalty!$A$3:$B$49,2,0) -> 3
A50: 2511-0049 | B50: MR311-R (Non AMS), Penetrant - Red; Solvent & Water Removable (1L) | C50: Non Destructive Testing | D50: Dye Penetrant Testing | E50: Penetrant | F50: MR311-R | G50: MR311-R | H50: NA | I50: NA | J50: 171042 | K50: BULK 5L | L50: BOX B2 | M50: 5 | N50: NON DG | O50: 171008 | P50: =VLOOKUP(F50,Royalty!$A$3:$B$49,2,0) -> 3
A51: 2511-0050 | B51: MR221, ECOLINE Magnetic Powder Concentrate - Black (1L) | C51: Non Destructive Testing | D51: Magnetic Particle Testing | E51: Detection Media (Visible) | F51: MR221 | G51: MR221 | H51: NA | I51: NA | J51: 172003 | K51: AEROSOL 400ML | L51: BOX A1 | M51: 10 | N51: UN1950 | O51: 172001 | P51: =VLOOKUP(F51,Royalty!$A$3:$B$49,2,0) -> 3
A52: 2511-0051 | B52: MR222LC, ECOLINE Magnetic Powder Concentrate - Red & Fluorescent (1L) | C52: Non Destructive Testing | D52: Magnetic Particle Testing | E52: Detection Media (Fluorescent) | F52: MR222LC | G52: MR222LC | H52: NA | I52: NA | J52: 172006 | K52: BULK 1KG | L52: BOX B1 | M52: 6 | N52: NON DG | O52: 172016 | P52: =VLOOKUP(F52,Royalty!$A$3:$B$49,2,0) -> 2
A53: 2511-0052 | B53: MR153, ECOLINE Magnetic Powder Concentrate - Fluorescent (1L) | C53: Non Destructive Testing | D53: Magnetic Particle Testing | E53: Detection Media (Fluorescent) | F53: MR153 | G53: MR153 | H53: NA | I53: NA | J53: 172018 | K53: BULK 1KG | L53: BOX B1 | M53: 6 | N53: NON DG | O53: 172015
A54: 2511-0053 | B54: MR158-R, ECOLINE Magnetic Powder Concentrate - Fluorescent (1L) | C54: Non Destructive Testing | D54: Magnetic Particle Testing | E54: Detection Media (Fluorescent) | F54: MR158-R | G54: MR158-R | H54: NA | I54: NA | J54: 172020 | K54: BULK 1KG | L54: BOX B1 | M54: 6 | N54: NON DG | O54: 172015 | P54: =VLOOKUP(F54,Royalty!$A$3:$B$49,2,0) -> 3
A55: 2511-0054 | B55: MR302, Corrosion Inhibitor Concentrate (1L) | C55: Non Destructive Testing | D55: Magnetic Particle Testing | E55: Additives | F55: MR302 | G55: MR302 | H55: NA | I55: NA | J55: 172032 | K55: BULK 1L | L55: BOX B1 | M55: 6 | N55: NON DG | O55: 172032
A56: 2511-0055 | B56: MR71, Paint Remover (1L) | C56: Non Destructive Testing | D56: Magnetic Particle Testing | E56: Cleaner | F56: MR71 | G56: MR71 | H56: NA | I56: NA | J56: 172036 | K56: BULK 1L | L56: BOX B1 | M56: 6 | N56: DG 3 | O56: 171039 | P56: =VLOOKUP(F56,Royalty!$A$3:$B$49,2,0) -> 3
A57: 2511-0056 | B57: MR670F, Penetrant - Flourescent Level 0.5; Solvent & Water Removable (205L) | C57: Non Destructive Testing | D57: Dye Penetrant Testing | E57: Penetrant | F57: MR670F | G57: MR670F | H57: NA | I57: NA | J57: 171002 | K57: BULK 205L | L57: BAR L1 | M57: 205 | N57: NON DG | O57: 171009 | P57: =VLOOKUP(F57,Royalty!$A$3:$B$49,2,0) -> 3
A58: 2511-0057 | B58: MR691F, Penetrant - Flourescent Level 1; Solvent & Water Removable (205L) | C58: Non Destructive Testing | D58: Dye Penetrant Testing | E58: Penetrant | F58: MR691F | G58: MR691F | H58: NA | I58: NA | J58: 171004 | K58: BULK 5L | L58: BOX B2 | M58: 5 | N58: NON DG | O58: 0
A59: 2511-0058 | B59: MR672F, Penetrant - Flourescent Level 2; Solvent & Water Removable (200L) | C59: Non Destructive Testing | D59: Dye Penetrant Testing | E59: Penetrant | F59: MR672F | G59: MR672F | H59: NA | I59: NA | J59: 171007 | K59: AEROSOL 400ML | L59: BOX A1 | M59: 10 | N59: UN1950 | O59: 0 | P59: =VLOOKUP(F59,Royalty!$A$3:$B$49,2,0) -> 2
A60: 2511-0059 | B60: MR682F, Penetrant - Flourescent Level 2; Solvent & Water Removable (205L) | C60: Non Destructive Testing | D60: Dye Penetrant Testing | E60: Penetrant | F60: MR682F | G60: MR682F | H60: NA | I60: NA | J60: 171009 | K60: BULK 1L | L60: BOX B1 | M60: 6 | N60: NON DG | O60: 0 | P60: =VLOOKUP(F60,Royalty!$A$3:$B$49,2,0) -> 2
A61: 2511-0060 | B61: MR683F, Penetrant - Flourescent Level 3; Solvent Removable (205L) | C61: Non Destructive Testing | D61: Dye Penetrant Testing | E61: Penetrant | F61: MR683F | G61: MR683F | H61: NA | I61: NA | J61: 171012 | K61: BULK 1L | L61: BOX B1 | M61: 1 | N61: NON DG | O61: 0 | P61: =VLOOKUP(F61,Royalty!$A$3:$B$49,2,0) -> 2
A62: 2511-0061 | B62: MR82, Flux Oil (AMS) (205L) | C62: Non Destructive Testing | D62: Magnetic Particle Testing | E62: Carrier Media | F62: MR82 | G62: MR82 | H62: NA | I62: NA | J62: 172029 | K62: BULK 205L | L62: BAR L1 | M62: 205 | N62: NON DG | O62: 172029 | P62: 0
A63: 2511-0062 | B63: MR82-R, ECOLINE Flux Oil (205L) | C63: Non Destructive Testing | D63: Magnetic Particle Testing | E63: Carrier Media | F63: MR82 | G63: MR82 | H63: NA | I63: NA | J63: 172031 | K63: BULK 205L | L63: BAR L1 | M63: 205 | N63: NON DG | O63: 172031 | P63: 0
A64: 2511-0063 | B64: MR82, Flux Oil (AMS) (25L) | C64: Non Destructive Testing | D64: Magnetic Particle Testing | E64: Carrier Media | F64: MR82 | G64: MR82 | H64: NA | I64: NA | J64: 172028 | K64: BULK 25L | L64: JAR J3 | M64: 25 | N64: NON DG | O64: 172028 | P64: 0
A65: 2511-0064 | B65: MR670F, Penetrant - Flourescent Level 0.5; Solvent & Water Removable (5L) | C65: Non Destructive Testing | D65: Dye Penetrant Testing | E65: Penetrant | F65: MR670F | G65: MR670F | H65: NA | I65: NA | J65: 171001 | K65: BULK 5L | L65: BOX B2 | M65: 5 | N65: NON DG | O65: 171006 | P65: =VLOOKUP(F65,Royalty!$A$3:$B$49,2,0) -> 3
A66: 2511-0065 | B66: MR691F, Penetrant - Flourescent Level 1; Solvent & Water Removable (5L) | C66: Non Destructive Testing | D66: Dye Penetrant Testing | E66: Penetrant | F66: MR691F | G66: MR691F | H66: NA | I66: NA | J66: 171003 | K66: AEROSOL 400ML | L66: BOX A1 | M66: 10 | N66: UN1950 | O66: 171005
A67: 2511-0066 | B67: MR672F, Penetrant - Flourescent Level 2; Solvent & Water Removable (5L) | C67: Non Destructive Testing | D67: Dye Penetrant Testing | E67: Penetrant | F67: MR672F | G67: MR672F | H67: NA | I67: NA | J67: 171006 | K67: BULK 200L | L67: BAR L1 | M67: 200 | N67: NON DG | O67: 171007 | P67: =VLOOKUP(F67,Royalty!$A$3:$B$49,2,0) -> 2
A68: 2511-0067 | B68: MR682F, Penetrant - Flourescent Level 2; Solvent & Water Removable (5L) | C68: Non Destructive Testing | D68: Dye Penetrant Testing | E68: Penetrant | F68: MR682F | G68: MR682F | H68: NA | I68: NA | J68: 171008 | K68: BULK 5L | L68: BOX B2 | M68: 5 | N68: NON DG | O68: 171001 | P68: =VLOOKUP(F68,Royalty!$A$3:$B$49,2,0) -> 2
A69: 2511-0068 | B69: MR683F, Penetrant - Flourescent Level 3; Solvent Removable (5L) | C69: Non Destructive Testing | D69: Dye Penetrant Testing | E69: Penetrant | F69: MR683F | G69: MR683F | H69: NA | I69: NA | J69: 171011 | K69: BULK 205L | L69: BAR L1 | M69: 205 | N69: NON DG | O69: 171002 | P69: =VLOOKUP(F69,Royalty!$A$3:$B$49,2,0) -> 2
A70: 2511-0069 | B70: MR62, Penetrant - Red; Solvent Removable (5L) | C70: Non Destructive Testing | D70: Dye Penetrant Testing | E70: Penetrant | F70: MR62 | G70: MR62 | H70: NA | I70: NA | J70: 171016 | K70: BULK 5L | L70: BOX B2 | M70: 5 | N70: NON DG | O70: 171021 | P70: =VLOOKUP(F70,Royalty!$A$3:$B$49,2,0) -> 2
A71: 2511-0070 | B71: MR67, ECOLINE Penetrant - Red; Solvent & Water Removable (5L) | C71: Non Destructive Testing | D71: Dye Penetrant Testing | E71: Penetrant | F71: MR67 | G71: MR67 | H71: NA | I71: NA | J71: 171021 | K71: BULK 1L | L71: BOX B1 | M71: 1 | N71: NON DG | O71: 171020 | P71: =VLOOKUP(F71,Royalty!$A$3:$B$49,2,0) -> 3
A72: 2511-0071 | B72: MR68NF, Biodegradable Penetrant – Red & Fluorescent; Solvent & Water Removable (5L) | C72: Non Destructive Testing | D72: Dye Penetrant Testing | E72: Penetrant | F72: MR68NF | G72: MR68NF | H72: NA | I72: NA | J72: 171024 | K72: BULK 5L | L72: BOX B2 | M72: 5 | N72: NON DG | O72: 171016 | P72: =VLOOKUP(F72,Royalty!$A$3:$B$49,2,0) -> 3
A73: 2511-0072 | B73: MR311-R AMS, Penetrant - Red; Solvent & Water Removable (5L) | C73: Non Destructive Testing | D73: Dye Penetrant Testing | E73: Penetrant | F73: MR311-R | G73: MR311-R | H73: NA | I73: NA | J73: 171027 | K73: AEROSOL 400ML | L73: BOX A1 | M73: 10 | N73: UN1950 | O73: 171014 | P73: =VLOOKUP(F73,Royalty!$A$3:$B$49,2,0) -> 3
A74: 2511-0073 | B74: MR70, Developer - White, Non Aqueous (5L) | C74: Non Destructive Testing | D74: Dye Penetrant Testing | E74: Developer | F74: MR70 | G74: MR70 | H74: NA | I74: NA | J74: 171030 | K74: BULK 1L | L74: BOX B1 | M74: 6 | N74: DG 3 | O74: 171032 | P74: =VLOOKUP(F74,Royalty!$A$3:$B$49,2,0) -> 3
A75: 2511-0074 | B75: MR70I, Developer - White, Non Aqueous (5L) | C75: Non Destructive Testing | D75: Dye Penetrant Testing | E75: Developer | F75: MR70I | G75: MR70I | H75: NA | I75: NA | J75: 171033 | K75: AEROSOL 400ML | L75: BOX A1 | M75: 1 | N75: UN1950 | O75: 171044 | P75: =VLOOKUP(F75,Royalty!$A$3:$B$49,2,0) -> 2
A76: 2511-0075 | B76: MR79, Special Remover (5L) | C76: Non Destructive Testing | D76: Dye Penetrant Testing | E76: Cleaner | F76: MR79 | G76: MR79 | H76: NA | I76: NA | J76: 171037 | K76: BULK 20L | L76: JAR J2 | M76: 20 | N76: DG 3 | O76: 0 | P76: =VLOOKUP(F76,Royalty!$A$3:$B$49,2,0) -> 3
A77: 2511-0076 | B77: MR85, Remover (5L) | C77: Non Destructive Testing | D77: Dye Penetrant Testing | E77: Cleaner | F77: MR85 | G77: MR85 | H77: NA | I77: NA | J77: 171040 | K77: BULK 5L | L77: BOX B2 | M77: 5 | N77: DG 3 | O77: 171037 | P77: =VLOOKUP(F77,Royalty!$A$3:$B$49,2,0) -> 3
A78: 2511-0077 | B78: MR311-R (Non AMS), Penetrant - Red; Solvent & Water Removable (5L) | C78: Non Destructive Testing | D78: Dye Penetrant Testing | E78: Penetrant | F78: MR311-R | G78: MR311-R | H78: NA | I78: NA | J78: 171043 | K78: BULK 1L | L78: BOX CL | M78: 1 | N78: NON DG | O78: 171015 | P78: =VLOOKUP(F78,Royalty!$A$3:$B$49,2,0) -> 3
A79: 2511-0078 | B79: MR153, ECOLINE Magnetic Powder Concentrate - Fluorescent (5L) | C79: Non Destructive Testing | D79: Magnetic Particle Testing | E79: Detection Media (Fluorescent) | F79: MR153 | G79: MR153 | H79: NA | I79: NA | J79: 172019 | K79: BULK 1KG | L79: BOX B1 | M79: 6 | N79: NON DG | O79: 172017
A80: 2511-0079 | B80: MR158-R, ECOLINE Magnetic Powder Concentrate - Fluorescent (5L) | C80: Non Destructive Testing | D80: Magnetic Particle Testing | E80: Detection Media (Fluorescent) | F80: MR158-R | G80: MR158-R | H80: NA | I80: NA | J80: 172021 | K80: BULK 1L | L80: BOX B1 | M80: 6 | N80: NON DG | O80: 0 | P80: =VLOOKUP(F80,Royalty!$A$3:$B$49,2,0) -> 3
A81: 2511-0080 | B81: MR82-R, ECOLINE Flux Oil (25L) | C81: Non Destructive Testing | D81: Magnetic Particle Testing | E81: Carrier Media | F81: MR82 | G81: MR82 | H81: NA | I81: NA | J81: 172030 | K81: BULK 5L | L81: BOX B2 | M81: 5 | N81: NON DG | O81: 172030 | P81: 0
A82: 2511-0081 | B82: MR302, Corrosion Inhibitor Concentrate (5L) | C82: Non Destructive Testing | D82: Magnetic Particle Testing | E82: Additives | F82: MR302 | G82: MR302 | H82: NA | I82: NA | J82: 172033 | K82: BULK 5L | L82: BOX B2 | M82: 5 | N82: NON DG | O82: 172033
A83: 2511-0082 | B83: MR71, Paint Remover (5L) | C83: Non Destructive Testing | D83: Magnetic Particle Testing | E83: Cleaner | F83: MR71 | G83: MR71 | H83: NA | I83: NA | J83: 172037 | K83: AEROSOL 400ML | L83: BOX A1 | M83: 10 | N83: UN1950 | O83: 171035 | P83: =VLOOKUP(F83,Royalty!$A$3:$B$49,2,0) -> 3
A84: 2511-0083 | B84: MR - SmartChoice, SC20 - Solvent Cleaner (280ml) | C84: Non Destructive Testing | D84: SmartChoice | E84: Dye Penetrant Testing | F84: SC-20 | G84: SC-20 | H84: NA | I84: NA | J84: 0 | K84: BULK 1L | L84: BOX CL | M84: 6 | N84: DG 3 | O84: 171036
A85: 2511-0084 | B85: MR - SmartChoice, SP10 - Solvent Removable Penetrant - Red (280ml) | C85: Non Destructive Testing | D85: SmartChoice | E85: Dye Penetrant Testing | F85: SP-10 | G85: SP-10 | H85: NA | I85: NA | J85: 0 | K85: AEROSOL 400ML | L85: BOX A1 | M85: 10 | N85: UN1950 | O85: 171022
A86: 2511-0085 | B86: MR115, Magnetic Powder Composition - Fluorescent 'high brilliance' (1Kg) | C86: Non Destructive Testing | D86: Magnetic Particle Testing | E86: Detection Media (Fluorescent) | F86: MR115 | G86: MR115 | H86: NA | I86: NA | J86: 172015 | K86: BULK 1L | L86: BOX B1 | M86: 6 | N86: NON DG | O86: 172018 | P86: =VLOOKUP(F86,Royalty!$A$3:$B$49,2,0) -> 2
A87: 2511-0086 | B87: MR913-B, Leak Detector concentrate, oil based (fluorescent - blue) (1L) | C87: Non Destructive Testing | D87: Leak Detection Systems | E87: Leak Detection Dye | F87: NA | G87: NA | H87: NA | I87: NA | J87: 0 | K87: BULK 1L | L87: BOX B1 | M87: 6 | N87: NON DG | O87: 0
A88: 2511-0087 | B88: MR913-G, Leak Detector concentrate, oil based (fluorescent - green) (1L) | C88: Non Destructive Testing | D88: Leak Detection Systems | E88: Leak Detection Dye | F88: NA | G88: NA | H88: NA | I88: NA | J88: 0 | K88: BULK 1L | L88: BOX B1 | M88: 6 | N88: NON DG | O88: 0
A89: 2511-0088 | B89: MR - SmartChoice, SD30 - Non-Aqueous Developer (5L) | C89: Non Destructive Testing | D89: SmartChoice | E89: Dye Penetrant Testing | F89: SD-30 | G89: SD-30 | H89: NA | I89: NA | J89: 0 | K89: AEROSOL 400ML | L89: BOX A1 | M89: 10 | N89: UN1950 | O89: 171031
A90: 2511-0089 | B90: MR - SmartChoice, SC20 - Solvent Cleaner (5L) | C90: Non Destructive Testing | D90: SmartChoice | E90: Dye Penetrant Testing | F90: SC-20 | G90: SC-20 | H90: NA | I90: NA | J90: 0 | K90: BULK 5L | L90: BOX B2 | M90: 5 | N90: DG 3 | O90: 172037
A91: 2511-0090 | B91: MR - SmartChoice, SP10 - Solvent Removable Penetrant - Red (5L) | C91: Non Destructive Testing | D91: SmartChoice | E91: Dye Penetrant Testing | F91: SP-10 | G91: SP-10 | H91: NA | I91: NA | J91: 0 | K91: BULK 25L | L91: JAR J3 | M91: 25 | N91: NON DG | O91: 171026
A92: 2511-0091 | B92: Klyde Rubber Insulation Coating - Blue (500ml) | C92: MRO Consumables | D92: Coatings | E92: NA | F92: Rubber Insulation Coating | G92: Rubber Insulation Coating | H92: NA | I92: NA | J92: 0 | K92: AEROSOL 500ML | L92: BOX A5 | M92: 12 | N92: UN1950 | O92: 0
A93: 2511-0092 | B93: EF-6Y AC Magnetic Yoke 230V 50-60 Hz, 1 Phase | C93: Non Destructive Testing | D93: Equipment & Accessories | E93: Yokes | F93: NA | G93: NA | H93: NA | I93: NA | J93: 0 | K93: ELECTRICAL | L93: BOX CE | M93: 1 | N93: NON DG | O93: 0
A94: 2511-0093 | B94: Klyde Rubber Insulation Coating - Yellow (500ml) | C94: MRO Consumables | D94: Coatings | E94: NA | F94: Zinc Spray | G94: Zinc Spray | H94: NA | I94: NA | J94: 0 | K94: AEROSOL 500ML | L94: BOX A5 | M94: 12 | N94: UN1950 | O94: 0
A95: 2511-0094 | B95: Klyde Flaky Zinc Spray 'Bright Grade' (500ml) | C95: MRO Consumables | D95: Corrosion Protection and Rust Prevention | E95: NA | F95: Zinc Spray | G95: Zinc Spray | H95: NA | I95: NA | J95: 0 | K95: AEROSOL 500ML | L95: BOX A5 | M95: 20 | N95: UN1950 | O95: 0
A96: 2511-0095 | B96: MR311-R, Penetrant - Red; Solvent & Water Removable (25L) | C96: Non Destructive Testing | D96: Dye Penetrant Testing | E96: Penetrant | F96: MR311-R | G96: MR311-R | H96: NA | I96: NA | J96: 171026 | K96: BULK 5L | L96: BOX B2 | M96: 5 | N96: NON DG | O96: 171027 | P96: =VLOOKUP(F96,Royalty!$A$3:$B$49,2,0) -> 3
A97: 2511-0096 | B97: MR114, Magnetic Powder Composition - Fluorescent (1Kg) | C97: Non Destructive Testing | D97: Magnetic Particle Testing | E97: Detection Media (Fluorescent) | F97: MR114 | G97: MR114 | H97: NA | I97: NA | J97: 172015 | K97: BULK 5L | L97: BOX B2 | M97: 5 | N97: NON DG | O97: 172019 | P97: =VLOOKUP(F97,Royalty!$A$3:$B$49,2,0) -> 2
A98: 2511-0097 | B98: MR111, ECOLINE Magnetic Powder - Fluorescent (1/2Kg) | C98: Non Destructive Testing | D98: Magnetic Particle Testing | E98: Detection Media (Fluorescent) | F98: MR111 | G98: MR111 | H98: NA | I98: NA | J98: 172011 | K98: BULK 1L | L98: BOX B1 | M98: 6 | N98: NON DG | O98: 172020 | P98: =VLOOKUP(F98,Royalty!$A$3:$B$49,2,0) -> 2
A99: 2511-0098 | B99: MR111, ECOLINE Magnetic Powder - Fluorescent (1Kg) | C99: Non Destructive Testing | D99: Magnetic Particle Testing | E99: Detection Media (Fluorescent) | F99: MR111 | G99: MR111 | H99: NA | I99: NA | J99: 172012 | K99: BULK 5L | L99: BOX B2 | M99: 5 | N99: NON DG | O99: 172021 | P99: =VLOOKUP(F99,Royalty!$A$3:$B$49,2,0) -> 2
A100: 2511-0099 | B100: MR117, Magnetic Powder Composition - Fluorescent (1Kg) | C100: Non Destructive Testing | D100: Magnetic Particle Testing | E100: Detection Media (Fluorescent) | F100: MR117 | G100: MR117 | H100: NA | I100: NA | J100: 172015 | K100: BULK 1KG | L100: JAR J6 | M100: 1 | N100: NON DG | O100: 172005
A101: 2511-0100 | B101: Klyde Aquakleen Concentrate (20L) | C101: MRO Consumables | D101: Cleaning and Degreasing | E101: Concentrates | F101: Aquakleen Conc. | G101: NA | H101: NA | I101: NA | J101: 0 | K101: BULK 20L | L101: JAR J2 | M101: 20 | N101: NON DG | O101: 0
A102: 2511-0101 | B102: Klyde K40 - Multifunctional Oil & Lubricant (General Maintainence) (500ml) | C102: MRO Consumables | D102: Lubricants and Penetrating Oils | E102: NA | F102: K40 | G102: K40 | H102: NA | I102: NA | J102: 0 | K102: AEROSOL 500ML | L102: BOX A5 | M102: 20 | N102: UN1950 | O102: 0
A103: 2511-0102 | B103: MR312, Penetrant - Red & Fluorescent; Solvent & Water Removable (Low temperature upto -30°C) (400ml) | C103: Non Destructive Testing | D103: Dye Penetrant Testing | E103: Penetrant | F103: MR312 | G103: MR312 | H103: NA | I103: NA | J103: 171022 | K103: AEROSOL 400ML | L103: BOX A1 | M103: 10 | N103: UN1950 | O103: 171025
A104: 2511-0103 | B104: MR76SH, Magnetic Powder Suspension - Black (High Temperature) (400 ml) | C104: Non Destructive Testing | D104: Magnetic Particle Testing | E104: Detection Media (Visible) | F104: MR76SH | G104: MR76SH | H104: NA | I104: NA | J104: 172001 | K104: AEROSOL 400ML | L104: BOX A1 | M104: 10 | N104: UN1950 | O104: 0 | P104: =VLOOKUP(F104,Royalty!$A$3:$B$49,2,0) -> 3
A105: 2511-0104 | B105: Klyde Flaky Zinc Spray 'Bright Grade' (400ml) | C105: MRO Consumables | D105: Corrosion Protection and Rust Prevention | E105: NA | F105: Zinc Spray | G105: Zinc Spray | H105: NA | I105: NA | J105: 0 | K105: AEROSOL 400ML | L105: BOX A5 | M105: 20 | N105: UN1950 | O105: 0
A106: 2511-0105 | B106: ASTM Test Block | C106: Non Destructive Testing | D106: Equipment & Accessories | E106: Guages & Test Blocks | F106: NA | G106: NA | H106: NA | I106: NA | J106: 0 | K106: ACCESSORY | L106: BOX CL | M106: 1 | N106: NON DG | O106: 0
A107: 2511-0106 | B107: MR653F, Penetrant - Flourescent Level 3; Solvent & Water Removable (400ml) | C107: Non Destructive Testing | D107: Dye Penetrant Testing | E107: Penetrant | F107: MR653F | G107: NA | H107: NA | I107: NA | J107: 171005 | K107: AEROSOL 400ML | L107: BOX A1 | M107: 10 | N107: UN1950 | O107: 172035
...

Sheet Sheet1

Sheet Royalty
A1: 3AK PRODUCTS | E1: Contract Products
A2: Annexure 3 | E2: Annexure 2
A3: MR70I | B3: 2 | C3: Annexure 3 | E3: MR311-R | F3: 3 | G3: Annexure 2
A4: MR110I | B4: 2 | C4: Annexure 3 | E4: MR85 | F4: 3 | G4: Annexure 2
A5: MR112 | B5: 2 | C5: Annexure 3 | E5: MR110 | F5: 3 | G5: Annexure 2
A6: MR115 | B6: 2 | C6: Annexure 3 | E6: MR158-R | F6: 3 | G6: Annexure 2
A7: MR214 | B7: 2 | C7: Annexure 3 | E7: MR210 | F7: 3 | G7: Annexure 2
A8: MR222PO | B8: 2 | C8: Annexure 3 | E8: MR221 | F8: 3 | G8: Annexure 2
A9: MR232 | B9: 2 | C9: Annexure 3 | E9: MR67 | F9: 3 | G9: Annexure 2
A10: MR304 | B10: 2 | C10: Annexure 3 | E10: MR670F | F10: 3 | G10: Annexure 2
A11: MR682F | B11: 2 | C11: Annexure 3 | E11: MR68H | F11: 3 | G11: Annexure 2
A12: MR76F | B12: 2 | C12: Annexure 3 | E12: MR68NF | F12: 3 | G12: Annexure 2
A13: MR62 | B13: 2 | C13: Annexure 3 | E13: MR70H | F13: 3 | G13: Annexure 2
A14: MR683F | B14: 2 | C14: Annexure 3 | E14: MR70 | F14: 3 | G14: Annexure 2
... A20: MR111 | B20: 2 | C20: Annexure 3 | E20: MR82 | F20: 3 | G20: Annexure 2
A21: MR114 | B21: 2 | C21: Annexure 3
A22: MR118 | B22: 2 | C22: Annexure 3
A23: MR222 | B23: 2 | C23: Annexure 3
A24: MR230 | B24: 2 | C24: Annexure 3
A25: MR233 | B25: 2 | C25: Annexure 3
A26: MR72 | B26: 2 | C26: Annexure 3
A27: MR111HB | B27: 2 | C27: Annexure 3
A28: MR114HB | B28: 2 | C28: Annexure 3
A29: MR153PL | B29: 2 | C29: Annexure 3
A30: MR222LC | B30: 2 | C30: Annexure 3
A31: MR231 | B31: 2 | C31: Annexure 3
A32: MR311-R | B32: 3 | C32: Annexure 2
... A49: MR82 | B49: 3 | C49: Annexure 2

Sheet Total ERP Item Dump
A1: SKU | B1: Desc | C1: Check
A2: No. | B2: Description | C2: =IFERROR(VLOOKUP(A2,'Product Categories for FG'!A:A,1,FALSE),"missing") -> missing
A3: 2510-0369 | B3: Rate Difference | C3: =IFERROR(VLOOKUP(A3,'Product Categories for FG'!A:A,1,FALSE),"missing") -> missing
A4: 2511-0001 | B4: MR672F, Penetrant - Flourescent Level 2; Solvent & Water Removable (400ml) | C4: =IFERROR(VLOOKUP(A4,'Product Categories for FG'!A:A,1,FALSE),"missing") -> 2511-0001
A5: 2511-0002 | B5: MR231, Dry Magnetic Powder - Grey (1Kg) | C5: =IFERROR(VLOOKUP(A5,'Product Categories for FG'!A:A,1,FALSE),"missing") -> 2511-0002
A6: 2511-0003 | B6: MR62, Penetrant - Red; Solvent Removable (400 ml) | C6: =IFERROR(VLOOKUP(A6,'Product Categories for FG'!A:A,1,FALSE),"missing") -> 2511-0003
A7: 2511-0004 | B7: MR68NF, Biodegradable Penetrant – Red & Fluorescent; Solvent & Water Removable (400ml) | C7: =IFERROR(VLOOKUP(A7,'Product Categories for FG'!A:A,1,FALSE),"missing") -> 2511-0004
A8: 2511-0005 | B8: MR311-R AMS, Penetrant - Red; Solvent & Water Removable (400 ml) | C8: =IFERROR(VLOOKUP(A8,'Product Categories for FG'!A:A,1,FALSE),"missing") -> 2511-0005
A9: 2511-0006 | B9: MR70, Developer - White, Non Aqueous (400 ml) | C9: =IFERROR(VLOOKUP(A9,'Product Categories for FG'!A:A,1,FALSE),"missing") -> 2511-0006
A10: 2511-0007 | B10: MR70I, Developer - White, Non Aqueous (400 ml) | C10: =IFERROR(VLOOKUP(A10,'Product Categories for FG'!A:A,1,FALSE),"missing") -> 2511-0007
A11: 2511-0008 | B11: MR79, Special Remover (400 ml) | C11: =IFERROR(VLOOKUP(A11,'Product Categories for FG'!A:A,1,FALSE),"missing") -> 2511-0008
A12: 2511-0009 | B12: MR85, Remover (400 ml) | C12: =IFERROR(VLOOKUP(A12,'Product Categories for FG'!A:A,1,FALSE),"missing") -> 2511-0009
A13: 2511-0010 | B13: MR311-R (Non AMS), Penetrant - Red; Solvent & Water Removable (400 ml) | C13: =IFERROR(VLOOKUP(A13,'Product Categories for FG'!A:A,1,FALSE),"missing") -> 2511-0010
... A281: 2511-0280 | B281: Magnetic Field Indicator Acc to ASTM E -709(Pie Guage) | C281: =IFERROR(VLOOKUP(A281,'Product Categories for FG'!A:A,1,FALSE),"missing") -> 2511-0280
A282: 2511-0281 | C282: =IFERROR(VLOOKUP(A282,'Product Categories for FG'!A:A,1,FALSE),"missing") -> 2511-0281
A283: 2511-0283 | B283: Penetrant Testing Flawed Specimen | C283: =IFERROR(VLOOKUP(A283,'Product Categories for FG'!A:A,1,FALSE),"missing") -> 2511-0283
A284: 2511-0284 | B284: Tam Panel Polished | C284: =IFERROR(VLOOKUP(A284,'Product Categories for FG'!A:A,1,FALSE),"missing") -> 2511-0284
A285: 2511-0285 | B285: Tam Panel Grit | C285: =IFERROR(VLOOKUP(A285,'Product Categories for FG'!A:A,1,FALSE),"missing") -> 2511-0285
A286: 2511-0286 | B286: Five Star Block (Type-2) | C286: =IFERROR(VLOOKUP(A286,'Product Categories for FG'!A:A,1,FALSE),"missing") -> 2511-0286
A287: 2511-0287 | B287: EF-2Y-230V AC Yoke | C287: =IFERROR(VLOOKUP(A287,'Product Categories for FG'!A:A,1,FALSE),"missing") -> 2511-0287
A288: 2511-0288 | B288: UV LED Torch without battery | C288: =IFERROR(VLOOKUP(A288,'Product Categories for FG'!A:A,1,FALSE),"missing") -> 2511-0288
A289: 2511-0289 | B289: PY -1 Permanent Magnetic Yoke | C289: =IFERROR(VLOOKUP(A289,'Product Categories for FG'!A:A,1,FALSE),"missing") -> 2511-0289
A290: 2511-0290 | B290: PY - 2 Permanent Magnetic Yoke | C290: =IFERROR(VLOOKUP(A290,'Product Categories for FG'!A:A,1,FALSE),"missing") -> 2511-0290
A291: 2511-0291 | B291: Magnetic Field Strength Meter MFM 200 | C291: =IFERROR(VLOOKUP(A291,'Product Categories for FG'!A:A,1,FALSE),"missing") -> 2511-0291
A292: 2511-0292 | B292: Articulation piece for articulated poles, for hand yoke MR® 56, MR® 56V42 MR® 56V110, 1 set = 2 piec | C292: =IFERROR(VLOOKUP(A292,'Product Categories for FG'!A:A,1,FALSE),"missing") -> 2511-0292
A293: 2511-0293 | B293: Contact pole for hand yoke MR® 56, MR® 56V42, MR® 56V110 1 set = 2 pieces | C293: =IFERROR(VLOOKUP(A293,'Product Categories for FG'!A:A,1,FALSE),"missing") -> 2511-0293
A294: 2511-0294 | B294: MR56 -1 | C294: =IFERROR(VLOOKUP(A294,'Product Categories for FG'!A:A,1,FALSE),"missing") -> 2511-0294
... A299: 2511-0299 | B299: Attblime Dental Scanning spray 200ml | C299: =IFERROR(VLOOKUP(A299,'Product Categories for FG'!A:A,1,FALSE),"missing") -> 2511-0299
A300: 2511-0300 | C300: =IFERROR(VLOOKUP(A300,'Product Categories for FG'!A:A,1,FALSE),"missing") -> missing
A301: 2511-0301 | B301: Reference Block Type 2 | C301: =IFERROR(VLOOKUP(A301,'Product Categories for FG'!A:A,1,FALSE),"missing") -> 2511-0301
A302: 2511-0302 | B302: MR® 67 Penetrant red and fluorescent(Jumbo- Pen) | C302: =IFERROR(VLOOKUP(A302,'Product Categories for FG'!A:A,1,FALSE),"missing") -> 2511-0302
A303: 2511-0303 | B303: MR 703 W Developer white(Jumbo-Pen) | C303: =IFERROR(VLOOKUP(A303,'Product Categories for FG'!A:A,1,FALSE),"missing") -> 2511-0303
A304: 2511-0304 | B304: MR68 C Penetrant red and fluorescent(Piccolo- Pen) | C304: =IFERROR(VLOOKUP(A304,'Product Categories for FG'!A:A,1,FALSE),"missing") -> 2511-0304
A305: 2511-0305 | B305: Exhibition Material | C305: =IFERROR(VLOOKUP(A305,'Product Categories for FG'!A:A,1,FALSE),"missing") -> 2511-0305
A306: 2511-0306 | B306: MRG, MR68 NF Penetrant red and fluorescent (500ml) | C306: =IFERROR(VLOOKUP(A306,'Product Categories for FG'!A:A,1,FALSE),"missing") -> 2511-0306
A307: 2511-0307 | B307: MRG, MR68 NF Penetrant red and fluorescent (5L) | C307: =IFERROR(VLOOKUP(A307,'Product Categories for FG'!A:A,1,FALSE),"missing") -> 2511-0307
A308: 2511-0308 | B308: MRG, MR70 AMS Developer white (500ml) | C308: =IFERROR(VLOOKUP(A308,'Product Categories for FG'!A:A,1,FALSE),"missing") -> 2511-0308
A309: 2511-0309 | B309: MRG: MR71 Paint Remover (500ml) | C309: =IFERROR(VLOOKUP(A309,'Product Categories for FG'!A:A,1,FALSE),"missing") -> 2511-0309
A310: 2511-0310 | B310: MRG, MR72 White Contrast Paint (500 ML) | C310: =IFERROR(VLOOKUP(A310,'Product Categories for FG'!A:A,1,FALSE),"missing") -> 2511-0310
A311: 2511-0311 | B311: MRG, MR76S Version S Magnetic powder suspension black (500ML) | C311: =IFERROR(VLOOKUP(A311,'Product Categories for FG'!A:A,1,FALSE),"missing") -> 2511-0311
A312: 2511-0312 | B312: MRG, MR88 AMS Remover (500ml) | C312: =IFERROR(VLOOKUP(A312,'Product Categories for FG'!A:A,1,FALSE),"missing") -> 2511-0312
... A429: 2511-0438 | B429: MR - SmartChoice, WCP40 CB White Contrast Background (400 ml) | C429: =IFERROR(VLOOKUP(A429,'Product Categories for FG'!A:A,1,FALSE),"missing") -> 2511-0438
C430: =IFERROR(VLOOKUP(A430,'Product Categories for FG'!A:A,1,FALSE),"missing") -> missing
C431: =IFERROR(VLOOKUP(A431,'Product Categories for FG'!A:A,1,FALSE),"missing") -> missing
C432: =IFERROR(VLOOKUP(A432,'Product Categories for FG'!A:A,1,FALSE),"missing") -> missing
C433: =IFERROR(VLOOKUP(A433,'Product Categories for FG'!A:A,1,FALSE),"missing") -> missing
C434: =IFERROR(VLOOKUP(A434,'Product Categories for FG'!A:A,1,FALSE),"missing") -> missing
C435: =IFERROR(VLOOKUP(A435,'Product Categories for FG'!A:A,1,FALSE),"missing") -> missing
C436: =IFERROR(VLOOKUP(A436,'Product Categories for FG'!A:A,1,FALSE),"missing") -> missing
C437: =IFERROR(VLOOKUP(A437,'Product Categories for FG'!A:A,1,FALSE),"missing") -> missing
C438: =IFERROR(VLOOKUP(A438,'Product Categories for FG'!A:A,1,FALSE),"missing") -> missing
C439: =IFERROR(VLOOKUP(A439,'Product Categories for FG'!A:A,1,FALSE),"missing") -> missing
C440: =IFERROR(VLOOKUP(A440,'Product Categories for FG'!A:A,1,FALSE),"missing") -> missing
C441: =IFERROR(VLOOKUP(A441,'Product Categories for FG'!A:A,1,FALSE),"missing") -> missing
C442: =IFERROR(VLOOKUP(A442,'Product Categories for FG'!A:A,1,FALSE),"missing") -> missing

Sheet Group Company List
A1: Company Name | B1: Surplus Royalty %
A2: Pacific Distribution FZE | B2: 1
A3: 3AK Chemie USA LLC | B3: 1.5
